zstreams/__init__.py
zstreams-0.0.2.dist-info/LICENSE
zstreams-0.0.2.dist-info/METADATA
zstreams-0.0.2.dist-info/WHEEL
zstreams-0.0.2.dist-info/top_level.txt
zstreams-0.0.2.dist-info/RECORD
