Metadata-Version: 2.1
Name: zstreams
Version: 0.0.2
Summary: Zeek Analysis Tools
Home-page: https://github.com/SuperCowPowers/zstreams
Author: Brian Wylie
Author-email: briford@supercowpowers.com
License: Apache
Keywords: Zeek,Bro,Python,Networking,Security,Spark,Kafka,Parquet
Platform: UNKNOWN
Classifier: Development Status :: 2 - Pre-Alpha
Classifier: Intended Audience :: Developers
Classifier: License :: OSI Approved :: Apache Software License
Classifier: Natural Language :: English
Classifier: Programming Language :: Python :: 3.6
Classifier: Programming Language :: Python :: 3.7
Classifier: Programming Language :: Python :: 3.8
Classifier: Programming Language :: Python :: Implementation :: CPython
Classifier: Programming Language :: Python :: Implementation :: PyPy
Requires-Dist: confluent-kafka
Requires-Dist: pyspark
